setup.py
normally_dist/Binomialdistribution.py
normally_dist/Gaussiandistribution.py
normally_dist/Generaldistribution.py
normally_dist/__init__.py
normally_dist.egg-info/PKG-INFO
normally_dist.egg-info/SOURCES.txt
normally_dist.egg-info/dependency_links.txt
normally_dist.egg-info/not-zip-safe
normally_dist.egg-info/top_level.txt