Metadata-Version: 1.0
Name: normally-dist
Version: 0.6
Summary: Gaussian and Binomial distributions
Home-page: UNKNOWN
Author: Ifenna
Author-email: UNKNOWN
License: UNKNOWN
Platform: UNKNOWN
